Workbook

Sheet Overview
B2: Aethos for Professional Services
B3: 10-Tenant E2E Demo & Test — Execution Tracker
B5: Companion to | C5: Aethos-PS-Test-Scenario-Library.md
B6: Platform | C6: https://aethos.ishirock.tech (agent-first PS ERP)
B7: Protocol | C7: Agentic-first (Atlas chat) -> Inbox approval -> UI evidence. Then verify manual fallback.
B8: Build rule | C8: No backend seeding. Every record created via signup / Atlas / CRUD and visible in a module screen.
B9: How to use | C9: Set Result per step on the Execution tab (Pass / Fail / Blocked / N/A). Summary updates automatically.
B10: Evidence triad | C10: Capture: (1) Atlas intent, (2) Inbox/approval card, (3) resulting record + report + Agent Run Ledger.
B12: Status legend
B13: Pass | C13: Fail | D13: Blocked | E13: N/A

Sheet Tenants
A1: The 10 Tenants
A3: # | B3: Tenant | C3: Market / Base ccy | D3: Firm type | E3: Size | F3: Complexity | G3: Signature dimension
A4: T1 | B4: Cobalt Consulting Co. | C4: US / USD | D4: Strategy boutique | E4: 8 | F4: Low | G4: Baseline smoke: T&M + one-offs, light SaaS procurement, monthly close
A5: T2 | B5: Pixel & Pulp Studio | C5: UK / GBP | D5: Creative + dev agency | E5: 30 | F5: Low-Med | G5: Milestone builds + multi-year retainers; capped-T&M overflow; EUR
A6: T3 | B6: Harborstone Accountants | C6: US / USD | D6: Accounting & tax firm | E6: 55 | F6: Med | G6: Fixed-fee milestones + per-event; scope creep; year-end statutory
A7: T4 | B7: Vantage Tax Partners | C7: Singapore / SGD | D7: Cross-border tax boutique | E7: 18 | F7: Med | G7: Multi-currency FX provenance; foreign-dividend journals; quarterly GST
A8: T5 | B8: Indus Engineering Advisory | C8: India / INR | D8: Engineering & PMO | E8: 90 | F8: Med-High | G8: 3-yr programs; HEAVY internal procurement; all AP edges; GST
A9: T6 | B9: Southern Cross Legal | C9: Australia / AUD | D9: Boutique law firm | E9: 22 | F9: Med | G9: Retainer-draw/trust; per-matter fixed; partial payments & disputes
A10: T7 | B10: Atlas Capital Advisors | C10: US / USD (+EUR/GBP) | D10: M&A / transaction advisory | E10: 40 | F10: High | G10: Success-fee milestones, estimate->actual; multi-currency deals
A11: T8 | B11: Helix Talent Group | C11: UK / GBP | D11: Recruitment & HR advisory | E11: 35 | F11: Med | G11: Per-placement + per-employee scaling + multi-year RPO retainers
A12: T9 | B12: Brightline Wealth Office | C12: UK / GBP (+SGD) | D12: Multi-entity family office | E12: 15 | F12: Very High | G12: One client = many entities; 7+ engagements; trusts; COSEC; privacy
A13: T10 | B13: Quantum Systems Integration | C13: US / USD (+EUR/GBP) | D13: Enterprise IT / SI | E13: 200 | F13: Extreme | G13: Everything: mixed-in-one engagement, full controls/audit, scheduled ops, red-team

Sheet Execution
A1: Execution Tracker
A2: Set Result per step. Capture the evidence triad. No backend seeding.
A4: Tenant | B4: Cycle | C4: Step | D4: Description (agentic-first action / prompt) | E4: Edge IDs | F4: Expected UI evidence | G4: Result | H4: Tester | I4: Date | J4: Notes
A5: T1 | B5: Setup | C5: S1.0 | D5: Sign up tenant (USD/US); create 4 roles; confirm tax + services; Stripe OFF first | F5: Tenant + users exist; Settings show tax rate
A6: T1 | B6: E2C | C6: S1.1 | D6: Atlas: log billable hours for Riverbend discovery | E6: EC-BILL-01 | F6: /time-entries row, billable
A7: T1 | B7: E2C | C7: S1.2 | D7: Atlas: process Riverbend travel receipt as billable expense | F7: /expenses row + receipt link
A8: T1 | B8: E2C | C8: S1.3 | D8: Atlas: June billing run -> Inbox -> approve | E8: EC-BILL-01 | F8: INV approved; DR AR/CR Revenue journal
A9: T1 | B9: E2C | C9: S1.4 | D9: Connect Stripe; Send; public link safety; pay test card; replay webhook | E9: EC-AR-06;EC-AGT-05 | F9: Invoice paid; DR Bank/CR AR; no duplicate payment
A10: T1 | B10: E2C | C10: S1.5 | D10: Calderon partial payment; Summit dual-approve race | E10: EC-AR-01;EC-CON-01 | F10: Remaining balance; one journal, loser 409
A11: T1 | B11: E2C | C11: S1.6 | D11: Velocity: AI-unavailable manual fallback invoice | E11: EC-AGT-04 | F11: Manual /invoices/new completes
A12: T1 | B12: E2C | C12: S1.7 | D12: Pinnacle zero-amount; Greenfield credit note | E12: EC-BILL-11;EC-BILL-12 | F12: No link/no-op; reverse journal
A13: T1 | B13: E2C | C13: S1.8 | D13: Northshore: Manager send blocked; Admin sends | E13: EC-RBAC-04 | F13: 403 for Manager; Admin/Owner sends
A14: T1 | B14: E2C | C14: S1.9 | D14: Collections read-only then draft >30d to Inbox; Hartwell cooldown | E14: EC-AR-04 | F14: Reminder cards in Inbox; cooldown blocked
A15: T1 | B15: P2P | C15: S1.10 | D15: SaaS bill intake -> approve -> bill-pay -> export -> sent -> settle | E15: EC-AP-12 | F15: DR Expense/CR AP; DR AP/CR Bank
A16: T1 | B16: R2R | C16: S1.11 | D16: Month-end close June -> lock; backdated post rejected | E16: EC-RR-01;EC-RR-04 | F16: Period lock; 422 period_locked
A17: T1 | B17: R2R | C17: S1.12 | D17: Statement package June vs May; reconcile to Reports | E17: EC-RR-13;EC-RR-14 | F17: TB balances; P&L/BS/CF render
A18: T1 | B18: Ctrl | C18: S1.13 | D18: Viewer approve attempt; decision trail; Agent Run Ledger | E18: EC-RBAC-01 | F18: Hidden + 403; trail + ledger reconcile
A19: T2 | B19: Setup | C19: S2.0 | D19: Sign up (GBP/UK); VAT20; Stripe on; roles | F19: Tenant/users; VAT seeded
A20: T2 | B20: E2C | C20: S2.1 | D20: Drop Aurora SOW -> engagement+project+rate card -> approve | F20: /engagements shows 3 milestones
A21: T2 | B21: E2C | C21: S2.2 | D21: Bill Milestone 1 then 2 across months | E21: EC-BILL-03 | F21: 2 invoices; WIP accrues between
A22: T2 | B22: E2C | C22: S2.3 | D22: Tideline 2-yr retainer run on the 1st -> Inbox -> approve | E22: EC-BILL-04 | F22: Recurring monthly retainer invoices
A23: T2 | B23: E2C | C23: S2.4 | D23: Beacon capped T&M: 89% alert then cap; overflow | E23: EC-BILL-06 | F23: Cap alert; non_billable_overflow
A24: T2 | B24: E2C | C24: S2.5 | D24: Kestrel mixed-model single invoice | E24: EC-BILL-07 | F24: Lines from fixed+retainer+T&M+expense
A25: T2 | B25: E2C | C25: S2.6 | D25: Lumiere EUR invoice; receipt FX move | E25: EC-FX-01;EC-FX-02 | F25: base_amount+fx_rate_id; realised FX 7900
A26: T2 | B26: E2C | C26: S2.7 | D26: Strata scope-creep supplemental engagement | E26: EC-BILL-10 | F26: Atlas cites comparable; new milestone
A27: T2 | B27: E2C | C27: S2.8 | D27: Verde learned-payer reminder suppression | E27: EC-AR-03 | F27: No reminder before learned pay day
A28: T2 | B28: P2P | C28: S2.9 | D28: Freelance subcontractor + recurring cloud bills | E28: EC-AP-11 | F28: 2nd cloud invoice auto-matches
A29: T2 | B29: P2P | C29: S2.10 | D29: Bill-pay lifecycle export->sent->settle | E29: EC-AP-12 | F29: Three recorded steps
A30: T2 | B30: R2R | C30: S2.11 | D30: Monthly close then Q2 package vs prior-yr Q2 | E30: EC-RR-01;EC-RR-02 | F30: Deterministic variances
A31: T2 | B31: R2R | C31: S2.12 | D31: Manual accrual journal; missing-reason rejected | E31: EC-RR-07;EC-RR-08 | F31: Posts w/ reason; 422 w/o
A32: T3 | B32: Setup | C32: S3.0 | D32: Sign up (USD); statutory+tax services; quarterly+YE | F32: COA/services set
A33: T3 | B33: E2C | C33: S3.1 | D33: Delmont 3-milestone annual accounts billed across year | E33: EC-BILL-03 | F33: Milestone recognition
A34: T3 | B34: E2C | C34: S3.2 | D34: Sandpiper per-event filings consolidated monthly | E34: EC-BILL-09 | F34: One consolidated invoice
A35: T3 | B35: E2C | C35: S3.3 | D35: Whitaker scope-creep supplemental | E35: EC-BILL-10 | F35: Comparable-fee citation
A36: T3 | B36: E2C | C36: S3.4 | D36: Sterling annual fee upfront -> deferred revenue | E36: EC-BILL-13 | F36: CR Deferred Revenue, released monthly
A37: T3 | B37: E2C | C37: S3.5 | D37: Foundry partial payment | E37: EC-AR-01 | F37: Remaining balance
A38: T3 | B38: P2P | C38: S3.6 | D38: Tax software + audit subcontractor; duplicate guard | E38: EC-AP-02;EC-AP-12 | F38: Approve-with-edits+reason; lifecycle
A39: T3 | B39: R2R | C39: S3.7 | D39: Monthly closes + Granite quarter-end review | E39: EC-RR-02 | F39: Comparative quarter
A40: T3 | B40: R2R | C40: S3.8 | D40: Year-end FY2026 close -> Inbox -> Owner approve | E40: EC-RR-03 | F40: year_end_close journal; dup blocked
A41: T3 | B41: R2R | C41: S3.9 | D41: Statement package + Statutory Pack FY26 vs FY25 | E41: EC-RR-13 | F41: TB balances; pack reconciles
A42: T3 | B42: R2R | C42: S3.10 | D42: Manual journal hi-value 2nd approver; reverse; edit blocked | E42: EC-RR-10;EC-RR-11;EC-RR-12 | F42: 2nd approver; reversal; 405
A43: T4 | B43: Setup | C43: S4.0 | D43: Sign up (SGD/SG); GST; confirm fx_rates | F43: GST seeded; FX present
A44: T4 | B44: E2C | C44: S4.1 | D44: Pacific Rim USD invoice; receipt FX move | E44: EC-FX-01;EC-FX-02 | F44: base+fx_rate_id; realised FX
A45: T4 | B45: E2C | C45: S4.2 | D45: Thistle first-time GBP invoice; missing-rate refusal | E45: EC-FX-04 | F45: Refuse if no rate
A46: T4 | B46: E2C | C46: S4.3 | D46: Kowloon stale-rate confirm | E46: EC-FX-03 | F46: Warning + explicit confirm
A47: T4 | B47: E2C | C47: S4.4 | D47: Harbourfront round-trip residual | E47: EC-FX-05 | F47: Residual to FX g/l; source untouched
A48: T4 | B48: P2P | C48: S4.5 | D48: Overseas correspondent foreign-ccy bill; lifecycle | E48: EC-AP-05;EC-AP-12 | F48: Base amount; FX lock toggle
A49: T4 | B49: R2R | C49: S4.6 | D49: Orchid SGD dividend manual journal -> Inbox approve | E49: EC-FX-06;EC-RR-10 | F49: Transaction+base+fx_rate_id; same-user denied
A50: T4 | B50: R2R | C50: S4.7 | D50: Quarterly GST close Q2 + comparative; multi-ccy toggle | E50: EC-RR-02 | F50: Statements reconcile; no silent missing rate
A51: T5 | B51: Setup | C51: S5.0 | D51: Sign up (INR/IN); GST; Owner money-out cap | F51: GST + cap configured
A52: T5 | B52: E2C | C52: S5.1 | D52: Deccan 3-yr milestone program; WIP accrual | E52: EC-BILL-03 | F52: Long-horizon milestones
A53: T5 | B53: E2C | C53: S5.2 | D53: Vindhya mixed (fixed+T&M) single invoice | E53: EC-BILL-07 | F53: Mixed lines
A54: T5 | B54: P2P | C54: S5.3 | D54: Survey EQUIPMENT invoice; code to asset; PO match | E54: EC-AP-03 | F54: Asset coding; PO match
A55: T5 | B55: P2P | C55: S5.4 | D55: Subcontractor invoice + duplicate guard | E55: EC-AP-02 | F55: Approve-with-edits + reason
A56: T5 | B56: P2P | C56: S5.5 | D56: Coastal no-PO service-order mismatch | E56: EC-AP-03 | F56: Draft until justified
A57: T5 | B57: P2P | C57: S5.6 | D57: Meghna multi-line mixed-GST bill | E57: EC-AP-10 | F57: Per-line tax + journal
A58: T5 | B58: P2P | C58: S5.7 | D58: Nilgiri vendor no bank details | E58: EC-AP-04 | F58: Blocked from batch
A59: T5 | B59: P2P | C59: S5.8 | D59: Saffron bill > balance threshold -> Owner approve | E59: EC-AP-09;EC-RBAC-03 | F59: Owner approval required
A60: T5 | B60: P2P | C60: S5.9 | D60: Konkan early-pay discount 2/10 net 30 | E60: EC-AP-07 | F60: Pay-date in window; credit line
A61: T5 | B61: P2P | C61: S5.10 | D61: Bharat export->sent->settle; regenerate file warning; partial | E61: EC-AP-12;EC-AP-08;EC-AP-06 | F61: 3 steps; idempotency warn; partially_paid
A62: T5 | B62: R2R | C62: S5.11 | D62: Monthly + Yamuna quarter-end (large WIP) | E62: EC-RR-02 | F62: WIP report reconciles
A63: T5 | B63: R2R | C63: S5.12 | D63: AP Aging clears; Cash Flow reflects outflows | F63: Aging + CF tie-out
A64: T6 | B64: Setup | C64: S6.0 | D64: Sign up (AUD/AU); GST; trust/retainer account | F64: GST + retainer set
A65: T6 | B65: E2C | C65: S6.1 | D65: Brindabella retainer-draw; floor warning | E65: EC-BILL-05 | F65: Negative 'retainer applied'; floor alert
A66: T6 | B66: E2C | C66: S6.2 | D66: Eureka draw floor warning + top-up | E66: EC-BILL-05 | F66: Floor warning
A67: T6 | B67: E2C | C67: S6.3 | D67: Coral/Banksia per-matter fixed; Banksia partial | E67: EC-BILL-02;EC-AR-01 | F67: Milestone fixed; remaining balance
A68: T6 | B68: E2C | C68: S6.4 | D68: Wattle disputed invoice -> collections hold | E68: EC-AR-02 | F68: No reminder until cleared
A69: T6 | B69: E2C | C69: S6.5 | D69: Federation per-filing consolidated | E69: EC-BILL-09 | F69: Consolidated invoice
A70: T6 | B70: P2P | C70: S6.6 | D70: Expert-witness subcontractor PO mismatch; court fees partial; research recurring | E70: EC-AP-03;EC-AP-06;EC-AP-11;EC-AP-12 | F70: Lifecycle + edges
A71: T6 | B71: R2R | C71: S6.7 | D71: Monthly close; Bondi backdated post into locked period | E71: EC-RR-04 | F71: 422 period_locked
A72: T6 | B72: R2R | C72: S6.8 | D72: Statement + management pack read-only reconcile | E72: EC-RR-13 | F72: No mutation; reconciles
A73: T7 | B73: Setup | C73: S7.0 | D73: Sign up (USD); EUR/GBP deal ccys; FX present | F73: FX seeded
A74: T7 | B74: E2C | C74: S7.1 | D74: Redwood success-fee milestone (estimated) | E74: EC-BILL-08 | F74: Estimated milestone
A75: T7 | B75: E2C | C75: S7.2 | D75: Redwood closes higher -> update milestone + invoice | E75: EC-BILL-08 | F75: Recomputed; partner approves
A76: T7 | B76: E2C | C76: S7.3 | D76: Hanseatic/Nordstern EUR deals; FX provenance | E76: EC-FX-01;EC-FX-02;EC-FX-04 | F76: Base amount; realised FX
A77: T7 | B77: E2C | C77: S7.4 | D77: Albion retainer + success-fee mix | E77: EC-BILL-07 | F77: Mixed invoice
A78: T7 | B78: E2C | C78: S7.5 | D78: Zenith escrow holdback as partial | E78: EC-AR-01 | F78: Remaining tracked
A79: T7 | B79: E2C | C79: S7.6 | D79: Sable aborted deal -> credit/courtesy | E79: EC-BILL-11;EC-BILL-12 | F79: No fee; credit
A80: T7 | B80: P2P | C80: S7.7 | D80: Data-room+travel+DD subcontractor; recurring auto-match | E80: EC-AP-11;EC-AP-12 | F80: Lifecycle
A81: T7 | B81: R2R | C81: S7.8 | D81: Quarterly close w/ deal spikes; comparative | E81: EC-RR-02 | F81: Variances
A82: T7 | B82: R2R | C82: S7.9 | D82: Year-end success-fee recognition -> Retained Earnings | E82: EC-RR-03;EC-RR-13 | F82: YE journal; statements
A83: T8 | B83: Setup | C83: S8.0 | D83: Sign up (GBP/UK); VAT | F83: VAT seeded
A84: T8 | B84: E2C | C84: S8.1 | D84: Halcyon 3-yr RPO retainer run | E84: EC-BILL-04 | F84: Recurring retainer
A85: T8 | B85: E2C | C85: S8.2 | D85: Northgate per-placement consolidated | E85: EC-BILL-09 | F85: One invoice
A86: T8 | B86: E2C | C86: S8.3 | D86: Pioneer per-employee scales with headcount | E86: EC-BILL-09 | F86: Next invoice scales
A87: T8 | B87: E2C | C87: S8.4 | D87: Cobblestone exec-search fixed | E87: EC-BILL-02 | F87: Milestone fixed
A88: T8 | B88: E2C | C88: S8.5 | D88: Camden fall-through credit; Vertex partial rebate | E88: EC-BILL-12;EC-AR-01 | F88: Credit note; remaining balance
A89: T8 | B89: E2C | C89: S8.6 | D89: Sterling Hotels EUR placement fee | E89: EC-FX-01 | F89: Base amount + provenance
A90: T8 | B90: E2C | C90: S8.7 | D90: Brookmere mixed; Lighthouse learned payer; Ashworth manual fallback | E90: EC-BILL-07;EC-AR-03;EC-AGT-04 | F90: Mixed; suppression; manual path
A91: T8 | B91: P2P | C91: S8.8 | D91: Job-board + background-check vendors; recurring auto-match | E91: EC-AP-11;EC-AP-12 | F91: Lifecycle
A92: T8 | B92: R2R | C92: S8.9 | D92: Monthly close; statements + utilization/headcount reporting | E92: EC-RR-01;EC-RR-13 | F92: Reconcile
A93: T9 | B93: Setup | C93: S9.0 | D93: Sign up (GBP+SGD); create 10 entities under family groups | F93: Entities mapped
A94: T9 | B94: E2C | C94: S9.1 | D94: Atlas: show family structure across 7+ engagements | F94: Unified multi-engagement view
A95: T9 | B95: E2C | C95: S9.2 | D95: Trading Group retainer; Investment Co + trusts fixed accounts | E95: EC-BILL-04;EC-BILL-02 | F95: Retainer + fixed
A96: T9 | B96: E2C | C96: S9.3 | D96: Trust(1992) SGD dividend manual journal; Marwood SG SGD invoice | E96: EC-FX-06;EC-FX-01 | F96: FX provenance
A97: T9 | B97: E2C | C97: S9.4 | D97: Sir Henry CGT scope-creep supplemental | E97: EC-BILL-10 | F97: Comparable-fee citation
A98: T9 | B98: E2C | C98: S9.5 | D98: Lady Marwood PII masking verified in agent evidence | E98: EC-OPS-02 | F98: Masked bank/tax IDs + names
A99: T9 | B99: E2C | C99: S9.6 | D99: COSEC per-event filings + deadline alerts; Foundation zero-fee; SIPP day-7 | E99: EC-BILL-09;EC-BILL-11;EC-AR-03 | F99: Events; alerts; pro-bono; payer
A100: T9 | B100: P2P | C100: S9.7 | D100: Disbursement/registry-fee vendor bills lifecycle | E100: EC-AP-12 | F100: Lifecycle
A101: T9 | B101: R2R | C101: S9.8 | D101: Quarterly consolidated close across entities; multi-ccy toggle | E101: EC-RR-02 | F101: Consolidated reporting
...

Sheet Summary
A1: Coverage Summary
A3: Metric | B3: Count
A4: Total steps | B4: =COUNTA(Execution!A5:A118)
A5: Pass | B5: =COUNTIF(Execution!$G$5:$G$118,"Pass")
A6: Fail | B6: =COUNTIF(Execution!$G$5:$G$118,"Fail")
A7: Blocked | B7: =COUNTIF(Execution!$G$5:$G$118,"Blocked")
A8: N/A | B8: =COUNTIF(Execution!$G$5:$G$118,"N/A")
A9: Not yet run | B9: =COUNTBLANK(Execution!$G$5:$G$118)
A10: Pass rate | B10: =IF(COUNTA(Execution!A5:A118)=0,0,COUNTIF(Execution!$G$5:$G$118,"Pass")/COUNTA(Execution!A5:A118))
A12: By tenant
A13: Tenant | B13: Steps | C13: Pass | D13: Fail | E13: Blocked | F13: Not run | G13: Pass rate
A14: T1 | B14: =COUNTIF(Execution!$A$5:$A$118,"T1") | C14: =COUNTIFS(Execution!$A$5:$A$118,"T1",Execution!$G$5:$G$118,"Pass") | D14: =COUNTIFS(Execution!$A$5:$A$118,"T1",Execution!$G$5:$G$118,"Fail") | E14: =COUNTIFS(Execution!$A$5:$A$118,"T1",Execution!$G$5:$G$118,"Blocked") | F14: =COUNTIFS(Execution!$A$5:$A$118,"T1",Execution!$G$5:$G$118,"") | G14: =IF(B14=0,0,C14/B14)
A15: T2 | B15: =COUNTIF(Execution!$A$5:$A$118,"T2") | C15: =COUNTIFS(Execution!$A$5:$A$118,"T2",Execution!$G$5:$G$118,"Pass") | D15: =COUNTIFS(Execution!$A$5:$A$118,"T2",Execution!$G$5:$G$118,"Fail") | E15: =COUNTIFS(Execution!$A$5:$A$118,"T2",Execution!$G$5:$G$118,"Blocked") | F15: =COUNTIFS(Execution!$A$5:$A$118,"T2",Execution!$G$5:$G$118,"") | G15: =IF(B15=0,0,C15/B15)
A16: T3 | B16: =COUNTIF(Execution!$A$5:$A$118,"T3") | C16: =COUNTIFS(Execution!$A$5:$A$118,"T3",Execution!$G$5:$G$118,"Pass") | D16: =COUNTIFS(Execution!$A$5:$A$118,"T3",Execution!$G$5:$G$118,"Fail") | E16: =COUNTIFS(Execution!$A$5:$A$118,"T3",Execution!$G$5:$G$118,"Blocked") | F16: =COUNTIFS(Execution!$A$5:$A$118,"T3",Execution!$G$5:$G$118,"") | G16: =IF(B16=0,0,C16/B16)
A17: T4 | B17: =COUNTIF(Execution!$A$5:$A$118,"T4") | C17: =COUNTIFS(Execution!$A$5:$A$118,"T4",Execution!$G$5:$G$118,"Pass") | D17: =COUNTIFS(Execution!$A$5:$A$118,"T4",Execution!$G$5:$G$118,"Fail") | E17: =COUNTIFS(Execution!$A$5:$A$118,"T4",Execution!$G$5:$G$118,"Blocked") | F17: =COUNTIFS(Execution!$A$5:$A$118,"T4",Execution!$G$5:$G$118,"") | G17: =IF(B17=0,0,C17/B17)
A18: T5 | B18: =COUNTIF(Execution!$A$5:$A$118,"T5") | C18: =COUNTIFS(Execution!$A$5:$A$118,"T5",Execution!$G$5:$G$118,"Pass") | D18: =COUNTIFS(Execution!$A$5:$A$118,"T5",Execution!$G$5:$G$118,"Fail") | E18: =COUNTIFS(Execution!$A$5:$A$118,"T5",Execution!$G$5:$G$118,"Blocked") | F18: =COUNTIFS(Execution!$A$5:$A$118,"T5",Execution!$G$5:$G$118,"") | G18: =IF(B18=0,0,C18/B18)
A19: T6 | B19: =COUNTIF(Execution!$A$5:$A$118,"T6") | C19: =COUNTIFS(Execution!$A$5:$A$118,"T6",Execution!$G$5:$G$118,"Pass") | D19: =COUNTIFS(Execution!$A$5:$A$118,"T6",Execution!$G$5:$G$118,"Fail") | E19: =COUNTIFS(Execution!$A$5:$A$118,"T6",Execution!$G$5:$G$118,"Blocked") | F19: =COUNTIFS(Execution!$A$5:$A$118,"T6",Execution!$G$5:$G$118,"") | G19: =IF(B19=0,0,C19/B19)
A20: T7 | B20: =COUNTIF(Execution!$A$5:$A$118,"T7") | C20: =COUNTIFS(Execution!$A$5:$A$118,"T7",Execution!$G$5:$G$118,"Pass") | D20: =COUNTIFS(Execution!$A$5:$A$118,"T7",Execution!$G$5:$G$118,"Fail") | E20: =COUNTIFS(Execution!$A$5:$A$118,"T7",Execution!$G$5:$G$118,"Blocked") | F20: =COUNTIFS(Execution!$A$5:$A$118,"T7",Execution!$G$5:$G$118,"") | G20: =IF(B20=0,0,C20/B20)
A21: T8 | B21: =COUNTIF(Execution!$A$5:$A$118,"T8") | C21: =COUNTIFS(Execution!$A$5:$A$118,"T8",Execution!$G$5:$G$118,"Pass") | D21: =COUNTIFS(Execution!$A$5:$A$118,"T8",Execution!$G$5:$G$118,"Fail") | E21: =COUNTIFS(Execution!$A$5:$A$118,"T8",Execution!$G$5:$G$118,"Blocked") | F21: =COUNTIFS(Execution!$A$5:$A$118,"T8",Execution!$G$5:$G$118,"") | G21: =IF(B21=0,0,C21/B21)
A22: T9 | B22: =COUNTIF(Execution!$A$5:$A$118,"T9") | C22: =COUNTIFS(Execution!$A$5:$A$118,"T9",Execution!$G$5:$G$118,"Pass") | D22: =COUNTIFS(Execution!$A$5:$A$118,"T9",Execution!$G$5:$G$118,"Fail") | E22: =COUNTIFS(Execution!$A$5:$A$118,"T9",Execution!$G$5:$G$118,"Blocked") | F22: =COUNTIFS(Execution!$A$5:$A$118,"T9",Execution!$G$5:$G$118,"") | G22: =IF(B22=0,0,C22/B22)
A23: T10 | B23: =COUNTIF(Execution!$A$5:$A$118,"T10") | C23: =COUNTIFS(Execution!$A$5:$A$118,"T10",Execution!$G$5:$G$118,"Pass") | D23: =COUNTIFS(Execution!$A$5:$A$118,"T10",Execution!$G$5:$G$118,"Fail") | E23: =COUNTIFS(Execution!$A$5:$A$118,"T10",Execution!$G$5:$G$118,"Blocked") | F23: =COUNTIFS(Execution!$A$5:$A$118,"T10",Execution!$G$5:$G$118,"") | G23: =IF(B23=0,0,C23/B23)
